abcai/__init__.py
abcai/main.py
abcai-1.8.2.dist-info/METADATA
abcai-1.8.2.dist-info/WHEEL
abcai-1.8.2.dist-info/entry_points.txt
abcai-1.8.2.dist-info/top_level.txt
abcai-1.8.2.dist-info/RECORD
