Metadata-Version: 2.1
Name: abcai
Version: 1.8.2
Summary: AI lab just import and run ⚡⚡⚡
